LICENSE
MANIFEST.in
README.rst
setup.py
pycoal/__init__.py
pycoal/environment.py
pycoal/mineral.py
pycoal/mining.py
pycoal.egg-info/PKG-INFO
pycoal.egg-info/SOURCES.txt
pycoal.egg-info/dependency_links.txt
pycoal.egg-info/namespace_packages.txt
pycoal.egg-info/not-zip-safe
pycoal.egg-info/requires.txt
pycoal.egg-info/top_level.txt