Metadata-Version: 1.1
Name: pycoal
Version: 0.5.2
Summary: COAL mining library for AVIRIS data.
Home-page: https://github.com/capstone-coal/pycoal
Author: COAL Capstone Develeopers
Author-email: coal-capstone@googlegroups.com
License: GNU GENERAL PUBLIC LICENSE, Version 2
Download-URL: http://pypi.python.org/pypi/pycoal/
Keywords: spectroscopy,aviris,aviris-ng,mining,minerals
Platform: UNKNOWN
Classifier: Environment :: Console
Classifier: Intended Audience :: Developers
Classifier: Intended Audience :: Information Technology
Classifier: Intended Audience :: Science/Research
Classifier: Topic :: Scientific/Engineering
Classifier: Development Status :: 4 - Beta
Classifier: License :: OSI Approved :: GNU General Public License v2 (GPLv2)
Classifier: Operating System :: OS Independent
Classifier: Programming Language :: Python
Classifier: Topic :: Software Development :: Libraries :: Python Modules
